{"authors.": {"authors": ["Raghavendra G", "Pranith Kumar K", "Amar Tumballi", "Shehjar Tikoo", "Anand Avati", "Vijay Bellur", "Raghavendra Bhat", "shishir", "Csaba Henk", "Krishnan Parthasarathi"], "commits": [872, 782, 781, 588, 537, 388, 378, 343, 331, 295], "id": [9, 45, 5, 3, 2, 22, 33, 46, 14, 60]}, "authors.last month": {"authors": ["Niels de Vos", "Emmanuel Dreyfus", "Xavier Hernandez", "Vijaykumar M", "Atin Mukherjee", "Pranith Kumar K", "Kaleb S. KEITHLEY", "Raghavendra Bhat", "Krutika Dhananjay", "Avra Sengupta"], "commits": [14, 13, 12, 9, 7, 6, 5, 5, 4, 3], "id": [80, 73, 156, 150, 185, 45, 86, 33, 121, 133]}, "authors.last year": {"authors": ["Pranith Kumar K", "Emmanuel Dreyfus", "Niels de Vos", "Harshavardhana Ranganath", "Xavier Hernandez", "Raghavendra G", "Krutika Dhananjay", "Kotresh H R", "Kaleb S. KEITHLEY", "Vijaykumar M"], "commits": [158, 110, 105, 88, 64, 61, 52, 51, 45, 45], "id": [45, 73, 80, 7, 156, 9, 121, 184, 86, 150]}}