{"actions": 28487, "added_lines": 1293809.0, "added_lines_30": 4638, "added_lines_365": 302150, "added_lines_7": 1199, "authors": 136, "authors_30": 28, "authors_365": 76, "authors_7": 14, "avg_commits_author": 63.1397, "avg_commits_month": 130.1061, "avg_files_author": 28.9706, "avg_files_month": 59.697, "branches": 10, "commits": 8587, "commits_30": 105, "commits_365": 1477, "commits_7": 26, "committers": 16, "diff_netadded_lines_30": -33503, "diff_netadded_lines_365": 81377, "diff_netadded_lines_7": 737, "diff_netauthors_30": -10, "diff_netauthors_365": 16, "diff_netauthors_7": 5, "diff_netcommits_30": -23, "diff_netcommits_365": 264, "diff_netcommits_7": 8, "diff_netfiles_30": -81, "diff_netfiles_365": 403, "diff_netfiles_7": 28, "diff_netremoved_lines_30": -1635, "diff_netremoved_lines_365": -24839, "diff_netremoved_lines_7": 479, "files": 3940, "files_30": 227, "files_365": 1608, "files_7": 62, "first_date": "2009-02-18", "last_date": "2014-08-25", "percentage_added_lines_30": 87, "percentage_added_lines_365": 36, "percentage_added_lines_7": 159, "percentage_authors_30": 26, "percentage_authors_365": 26, "percentage_authors_7": 55, "percentage_commits_30": 17, "percentage_commits_365": 21, "percentage_commits_7": 44, "percentage_files_30": 26, "percentage_files_365": 33, "percentage_files_7": 82, "percentage_removed_lines_30": 42, "percentage_removed_lines_365": 18, "percentage_removed_lines_7": 412, "removed_lines": 668424.0, "removed_lines_30": 2179, "removed_lines_365": 107597, "removed_lines_7": 595, "repositories": 1}