{"senders.": {"id": [73, 157, 22, 2, 80, 45, 74, 40050, 7, 37654], "senders": ["Emmanuel Dreyfus", "Justin Clift", "Vijay Bellur", "Anand Avati", "Niels de Vos", "Pranith Kumar K", "Jeff Darcy", "johnmark@gluster.org", "Harshavardhana Ranganath", "gordan"], "sent": [830, 672, 660, 636, 412, 406, 293, 270, 234, 219]}, "senders.last month": {"id": [73, 80, 22, 60, 74, 185, 177, 156, 41086, 62], "senders": ["Emmanuel Dreyfus", "Niels de Vos", "Vijay Bellur", "Krishnan Parthasarathi", "Jeff Darcy", "Atin Mukherjee", "ShyamsundarR", "Xavier Hernandez", "dmcallis@redhat.com", "Venky Shankar"], "sent": [51, 38, 27, 22, 20, 18, 15, 15, 14, 14]}, "senders.last year": {"id": [157, 45, 73, 80, 22, 7, 74, 158, 81, 40592], "senders": ["Justin Clift", "Pranith Kumar K", "Emmanuel Dreyfus", "Niels de Vos", "Vijay Bellur", "Harshavardhana Ranganath", "Jeff Darcy", "Lalatendu Mohanty", "Kaleb KEITHLEY", "purpleidea@gmail.com"], "sent": [568, 319, 315, 314, 306, 173, 149, 141, 125, 113]}}