{"closers.": {"closed": [1500, 450, 260, 232, 221, 206, 203, 158, 132, 117], "closers": ["Amar Tumballi", "Niels de Vos", "Vijay Bellur", "shishir gowda", "Shehjar Tikoo", "Raghavendra G", "Pranith Kumar K", "Raghavendra Bhat", "Anand Avati", "Lakshmipathi G"], "id": [241, 596, 237, 346, 246, 244, 341, 269, 247, 291]}, "closers.last month": {"closed": [91, 5, 4, 2, 1, 1, 1, 1, 1, 1], "closers": ["Niels de Vos", "Ravishankar N", "Pranith Kumar K", "Kaleb KEITHLEY", "Aravinda VK", "Ben England", "Darshan", "Kaushal", "Martin Kudlej", "santosh pradhan"], "id": [596, 1011, 341, 665, 1232, 1041, 1696, 9654, 1441, 847]}, "closers.last year": {"closed": [444, 31, 24, 13, 7, 7, 7, 6, 5, 5], "closers": ["Niels de Vos", "Martin Kudlej", "Kaleb KEITHLEY", "Pranith Kumar K", "Poornima G", "Ravishankar N", "Vivek Agarwal", "Justin Clift", "Amar Tumballi", "santosh pradhan"], "id": [596, 1441, 665, 341, 1212, 1011, 925, 832, 241, 847]}, "openers.": {"id": [33, 45, 5, 42, 9, 44, 65, 9608, 592, 9659], "opened": [287, 209, 198, 191, 159, 151, 128, 117, 110, 110], "openers": ["Raghavendra Bhat", "Pranith Kumar K", "Amar Tumballi", "Anush Shetty", "Raghavendra G", "Lakshmipathi G", "Vishwanath", "Harshavardhana", "Shwetha Panduranga", "shylesh"]}, "openers.last month": {"id": [80, 45, 156, 231, 185, 1033, 335, 81, 133, 9654], "opened": [9, 8, 8, 7, 6, 5, 5, 4, 3, 3], "openers": ["Niels de Vos", "Pranith Kumar K", "Xavier Hernandez", "Anders Blomdell", "Atin Mukherjee", "hchiramm", "joe", "Kaleb KEITHLEY", "Avra Sengupta", "Kaushal"]}, "openers.last year": {"id": [80, 45, 133, 81, 9654, 157, 62, 335, 145, 1440], "opened": [58, 56, 38, 38, 32, 27, 27, 26, 24, 22], "openers": ["Niels de Vos", "Pranith Kumar K", "Avra Sengupta", "Kaleb KEITHLEY", "Kaushal", "Justin Clift", "Venky Shankar", "joe", "Ravishankar N", "Kotresh HR"]}}