{"allhistory_participants": 1044, "changed": 4471, "changers": 510, "closed": 3579, "closed_14": 21, "closed_180": 78, "closed_30": 30, "closed_365": 1096, "closed_60": 46, "closed_7": 19, "closed_730": 1515, "closed_90": 53, "closers": 99, "closers_14": 4, "closers_180": 23, "closers_30": 7, "closers_365": 42, "closers_60": 13, "closers_7": 3, "closers_730": 69, "closers_90": 14, "companies": 2, "diff_netchangers_30": -9, "diff_netchangers_365": 71, "diff_netchangers_7": -5, "diff_netclosed_30": 14, "diff_netclosed_365": 616, "diff_netclosed_7": -17, "diff_netclosers_30": -3, "diff_netclosers_365": -5, "diff_netclosers_7": 0, "diff_netopened_30": 24, "diff_netopened_365": -70, "diff_netopened_7": 5, "first_date": "2009-05-29", "last_date": "2014-03-07", "opened": 4589, "opened_14": 33, "opened_180": 433, "opened_30": 99, "opened_365": 944, "opened_60": 174, "opened_7": 20, "opened_730": 1973, "opened_90": 230, "openers": 544, "percentage_changers_30": 13, "percentage_changers_365": 36, "percentage_changers_7": 29, "percentage_closed_30": 87, "percentage_closed_365": 128, "percentage_closed_7": 89, "percentage_closers_30": 30, "percentage_closers_365": 10, "percentage_closers_7": 0, "percentage_opened_30": 34, "percentage_opened_365": 6, "percentage_opened_7": 41, "trackers": 1, "type": "bugzilla", "url": "https://bugzilla.redhat.com/buglist.cgi?product=GlusterFS"}