{"companies": 7, "diff_netsenders_30": -11, "diff_netsenders_365": 108, "diff_netsenders_7": -4, "diff_netsent_30": 3, "diff_netsent_365": 3151, "diff_netsent_7": -13, "first_date": "2009-02-18", "last_date": "2014-12-24", "percentage_senders_30": 7, "percentage_senders_365": 19, "percentage_senders_7": 6, "percentage_sent_30": 0, "percentage_sent_365": 62, "percentage_sent_7": 7, "repositories": 4, "senders": 2331, "senders_30": 134, "senders_365": 670, "senders_7": 56, "senders_init": 1966, "senders_response": 1561, "sent": 26676, "sent_30": 759, "sent_365": 8168, "sent_7": 164, "sent_response": 20039, "threads": 17057}