{"companies": 3, "diff_netsenders_30": -3, "diff_netsenders_365": 129, "diff_netsenders_7": -3, "diff_netsent_30": 35, "diff_netsent_365": 573, "diff_netsent_7": -5, "first_date": "2009-02-18", "last_date": "2014-03-29", "percentage_senders_30": 2, "percentage_senders_365": 28, "percentage_senders_7": 6, "percentage_sent_30": 8, "percentage_sent_365": 13, "percentage_sent_7": 4, "repositories": 2, "senders": 1954, "senders_14": 70, "senders_180": 367, "senders_30": 112, "senders_365": 604, "senders_60": 177, "senders_7": 41, "senders_730": 940, "senders_90": 223, "senders_init": 1657, "senders_response": 1290, "sent": 19489, "sent_14": 234, "sent_180": 2275, "sent_30": 439, "sent_365": 4918, "sent_60": 840, "sent_7": 115, "sent_730": 9259, "sent_90": 1276, "sent_response": 14338, "threads": 12266}