{"companies": 7, "diff_netsenders_30": 9, "diff_netsenders_365": 133, "diff_netsenders_7": 11, "diff_netsent_30": 101, "diff_netsent_365": 3153, "diff_netsent_7": 35, "first_date": "2009-02-18", "last_date": "2014-11-13", "percentage_senders_30": 7, "percentage_senders_365": 24, "percentage_senders_7": 19, "percentage_sent_30": 17, "percentage_sent_365": 67, "percentage_sent_7": 23, "repositories": 4, "senders": 2291, "senders_30": 136, "senders_365": 677, "senders_7": 67, "senders_init": 1937, "senders_response": 1524, "sent": 25644, "sent_30": 690, "sent_365": 7858, "sent_7": 183, "sent_response": 19220, "threads": 16363}