{"companies": 3, "diff_netsenders_30": -11, "diff_netsenders_365": 144, "diff_netsenders_7": -8, "diff_netsent_30": 45, "diff_netsent_365": 686, "diff_netsent_7": 0, "first_date": "2009-02-18", "last_date": "2014-04-17", "percentage_senders_30": 9, "percentage_senders_365": 32, "percentage_senders_7": 17, "percentage_sent_30": 11, "percentage_sent_365": 15, "percentage_sent_7": 0, "repositories": 2, "senders": 1973, "senders_14": 68, "senders_180": 349, "senders_30": 110, "senders_365": 611, "senders_60": 182, "senders_7": 37, "senders_730": 939, "senders_90": 228, "senders_init": 1675, "senders_response": 1306, "sent": 19744, "sent_14": 188, "sent_180": 2329, "sent_30": 441, "sent_365": 4991, "sent_60": 838, "sent_7": 92, "sent_730": 9291, "sent_90": 1313, "sent_response": 14523, "threads": 12427}