{"companies": 3, "diff_netsenders_30": 18, "diff_netsenders_365": 135, "diff_netsenders_7": 1, "diff_netsent_30": -105, "diff_netsent_365": 532, "diff_netsent_7": 33, "first_date": "2009-02-18", "last_date": "2014-03-14", "percentage_senders_30": 17, "percentage_senders_365": 30, "percentage_senders_7": 2, "percentage_sent_30": 20, "percentage_sent_365": 12, "percentage_sent_7": 44, "repositories": 2, "senders": 1936, "senders_14": 65, "senders_180": 380, "senders_30": 120, "senders_365": 607, "senders_60": 171, "senders_7": 43, "senders_730": 935, "senders_90": 214, "senders_init": 1640, "senders_response": 1275, "sent": 19254, "sent_14": 182, "sent_180": 2341, "sent_30": 389, "sent_365": 4846, "sent_60": 891, "sent_7": 107, "sent_730": 9143, "sent_90": 1165, "sent_response": 14165, "threads": 12122}