{"diff_netsenders_30": 4, "diff_netsenders_365": 18, "diff_netsenders_7": -5, "diff_netsent_30": 82, "diff_netsent_365": 2135, "diff_netsent_7": -11, "first_date": "2009-02-18", "last_date": "2014-11-11", "percentage_senders_30": 15, "percentage_senders_365": 43, "percentage_senders_7": 27, "percentage_sent_30": 37, "percentage_sent_365": 155, "percentage_sent_7": 15, "repositories": 4, "senders": 78, "senders_30": 30, "senders_365": 59, "senders_7": 13, "senders_init": 42, "senders_response": 78, "sent": 7152, "sent_30": 301, "sent_365": 3505, "sent_7": 58, "sent_response": 6508, "threads": 6038}