{"actions": 30941, "added_lines": 1443020.0, "added_lines_30": 46404, "added_lines_365": 298270, "added_lines_7": 4182, "authors": 147, "authors_30": 39, "authors_365": 85, "authors_7": 24, "avg_commits_author": 63.4354, "avg_commits_month": 139.1791, "avg_files_author": 31.0408, "avg_files_month": 68.1045, "branches": 12, "commits": 9325, "commits_30": 226, "commits_365": 1729, "commits_7": 74, "committers": 25, "companies": 3, "core": 25, "diff_netadded_lines_30": 38909, "diff_netadded_lines_365": 30485, "diff_netadded_lines_7": -5905, "diff_netauthors_30": 9, "diff_netauthors_365": 16, "diff_netauthors_7": 5, "diff_netcommits_30": 109, "diff_netcommits_365": 130, "diff_netcommits_7": 16, "diff_netfiles_30": 97, "diff_netfiles_365": 396, "diff_netfiles_7": 3, "diff_netremoved_lines_30": 24714, "diff_netremoved_lines_365": -2863, "diff_netremoved_lines_7": -856, "files": 4563, "files_30": 374, "files_365": 1908, "files_7": 118, "first_date": "2009-02-18", "last_date": "2014-09-28", "occasional": 90, "percentage_added_lines_30": 519, "percentage_added_lines_365": 11, "percentage_added_lines_7": 58, "percentage_authors_30": 30, "percentage_authors_365": 23, "percentage_authors_7": 26, "percentage_commits_30": 93, "percentage_commits_365": 8, "percentage_commits_7": 27, "percentage_files_30": 35, "percentage_files_365": 26, "percentage_files_7": 2, "percentage_removed_lines_30": 591, "percentage_removed_lines_365": 2, "percentage_removed_lines_7": 32, "regular": 32, "removed_lines": 745945.0, "removed_lines_30": 28895, "removed_lines_365": 131206, "removed_lines_7": 1766, "repositories": 3, "type": "git", "url": "git://git.gluster.org/glusterfs"}